utilities/__init__.py
utilities/due_date.py
utilities/email_report.py
utilities/submission_date.py
utilities/uniq_claim_id.py
claim_function_library-0.1.0.dist-info/LICENSE
claim_function_library-0.1.0.dist-info/METADATA
claim_function_library-0.1.0.dist-info/WHEEL
claim_function_library-0.1.0.dist-info/top_level.txt
claim_function_library-0.1.0.dist-info/RECORD
