Metadata-Version: 2.1
Name: claim-function-library
Version: 0.1.0
Summary: A collection of utility functions for claim submission app
Author: Ritika Chatterjee
Author-email: ritikachat19@gmail.com
Classifier: Programming Language :: Python :: 3
Classifier: License :: OSI Approved :: MIT License
Classifier: Operating System :: OS Independent
Requires-Python: >=3.6
License-File: LICENSE
